{
	"name": "ingestion",
	"properties": {
		"activities": [
			{
				"name": "last_cdc",
				"type": "Lookup",
				"dependsOn": [],
				"policy": {
					"timeout": "0.12:00:00",
					"retry": 0,
					"retryIntervalInSeconds": 30,
					"secureOutput": false,
					"secureInput": false
				},
				"userProperties": [],
				"typeProperties": {
					"source": {
						"type": "JsonSource",
						"storeSettings": {
							"type": "AzureBlobFSReadSettings",
							"recursive": true,
							"enablePartitionDiscovery": false
						},
						"formatSettings": {
							"type": "JsonReadSettings"
						}
					},
					"dataset": {
						"referenceName": "ds_cdc",
						"type": "DatasetReference"
					},
					"firstRowOnly": false
				}
			},
			{
				"name": "TotalResults",
				"type": "Script",
				"dependsOn": [
					{
						"activity": "last_cdc",
						"dependencyConditions": [
							"Succeeded"
						]
					}
				],
				"policy": {
					"timeout": "0.12:00:00",
					"retry": 0,
					"retryIntervalInSeconds": 30,
					"secureOutput": false,
					"secureInput": false
				},
				"userProperties": [],
				"linkedServiceName": {
					"referenceName": "ls_Database",
					"type": "LinkedServiceReference"
				},
				"typeProperties": {
					"scripts": [
						{
							"type": "Query",
							"text": {
								"value": "SELECT COUNT(*) AS total_Count\nFROM @{pipeline().parameters.schema}.@{pipeline().parameters.table}\nWHERE last_updated > '@{if(empty(pipeline().parameters.backdate), activity('last_cdc').output.value[0].cdc_timestamp, pipeline().parameters.backdate)}'",
								"type": "Expression"
							}
						}
					],
					"scriptBlockExecutionTimeout": "02:00:00"
				}
			},
			{
				"name": "if_new_Rows",
				"type": "IfCondition",
				"dependsOn": [
					{
						"activity": "TotalResults",
						"dependencyConditions": [
							"Succeeded"
						]
					}
				],
				"userProperties": [],
				"typeProperties": {
					"expression": {
						"value": "@greater(activity('TotalResults').output.resultSets[0].rows[0].total_count, 0)",
						"type": "Expression"
					},
					"ifTrueActivities": [
						{
							"name": "load",
							"type": "Copy",
							"dependsOn": [],
							"policy": {
								"timeout": "0.12:00:00",
								"retry": 0,
								"retryIntervalInSeconds": 30,
								"secureOutput": false,
								"secureInput": false
							},
							"userProperties": [],
							"typeProperties": {
								"source": {
									"type": "AzureSqlSource",
									"sqlReaderQuery": {
										"value": "SELECT *\nFROM @{pipeline().parameters.schema}.@{pipeline().parameters.table}\nWHERE last_updated > '@{if(empty(pipeline().parameters.backdate), activity('last_cdc').output.value[0].cdc_timestamp, pipeline().parameters.backdate)}'",
										"type": "Expression"
									},
									"queryTimeout": "02:00:00",
									"partitionOption": "None"
								},
								"sink": {
									"type": "ParquetSink",
									"storeSettings": {
										"type": "AzureBlobFSWriteSettings"
									},
									"formatSettings": {
										"type": "ParquetWriteSettings"
									}
								},
								"enableStaging": false,
								"translator": {
									"type": "TabularTranslator",
									"typeConversion": true,
									"typeConversionSettings": {
										"allowDataTruncation": true,
										"treatBooleanAsNumber": false
									}
								}
							},
							"inputs": [
								{
									"referenceName": "ds_database",
									"type": "DatasetReference"
								}
							],
							"outputs": [
								{
									"referenceName": "ds_parquet",
									"type": "DatasetReference"
								}
							]
						},
						{
							"name": "change_cdc",
							"type": "Copy",
							"dependsOn": [
								{
									"activity": "max",
									"dependencyConditions": [
										"Succeeded"
									]
								}
							],
							"policy": {
								"timeout": "0.12:00:00",
								"retry": 0,
								"retryIntervalInSeconds": 30,
								"secureOutput": false,
								"secureInput": false
							},
							"userProperties": [],
							"typeProperties": {
								"source": {
									"type": "JsonSource",
									"additionalColumns": [
										{
											"name": "cdc_timestamp",
											"value": {
												"value": "@activity('max').output.resultSets[0].rows[0].cdc_timestamp",
												"type": "Expression"
											}
										}
									],
									"storeSettings": {
										"type": "AzureBlobFSReadSettings",
										"recursive": true,
										"enablePartitionDiscovery": false
									},
									"formatSettings": {
										"type": "JsonReadSettings"
									}
								},
								"sink": {
									"type": "JsonSink",
									"storeSettings": {
										"type": "AzureBlobFSWriteSettings"
									},
									"formatSettings": {
										"type": "JsonWriteSettings"
									}
								},
								"enableStaging": false
							},
							"inputs": [
								{
									"referenceName": "ds_emptyjson",
									"type": "DatasetReference"
								}
							],
							"outputs": [
								{
									"referenceName": "ds_cdc",
									"type": "DatasetReference"
								}
							]
						},
						{
							"name": "max",
							"type": "Script",
							"dependsOn": [
								{
									"activity": "load",
									"dependencyConditions": [
										"Succeeded"
									]
								}
							],
							"policy": {
								"timeout": "0.12:00:00",
								"retry": 0,
								"retryIntervalInSeconds": 30,
								"secureOutput": false,
								"secureInput": false
							},
							"userProperties": [],
							"linkedServiceName": {
								"referenceName": "ls_Database",
								"type": "LinkedServiceReference"
							},
							"typeProperties": {
								"scripts": [
									{
										"type": "Query",
										"text": {
											"value": "SELECT MAX(last_updated) as cdc_timestamp FROM @{pipeline().parameters.schema}.@{pipeline().parameters.table}",
											"type": "Expression"
										}
									}
								],
								"scriptBlockExecutionTimeout": "02:00:00"
							}
						}
					]
				}
			}
		],
		"parameters": {
			"schema": {
				"type": "string",
				"defaultValue": "dbo"
			},
			"table": {
				"type": "string",
				"defaultValue": "source_orders"
			},
			"backdate": {
				"type": "string",
				"defaultValue": "2025-09-25"
			}
		},
		"variables": {
			"test": {
				"type": "String"
			}
		},
		"annotations": [],
		"lastPublishTime": "2026-05-30T19:01:59Z"
	},
	"type": "Microsoft.DataFactory/factories/pipelines"
}